setup.py
auto_basic_server/__init__.py
auto_basic_server/main.py
auto_basic_server.egg-info/PKG-INFO
auto_basic_server.egg-info/SOURCES.txt
auto_basic_server.egg-info/dependency_links.txt
auto_basic_server.egg-info/not-zip-safe
auto_basic_server.egg-info/top_level.txt
auto_basic_server/common/__init__.py
auto_basic_server/common/autocfg.py
auto_basic_server/common/autofile.py
auto_basic_server/common/autogui.py
auto_basic_server/common/autoinput.py
auto_basic_server/common/autoproc.py
auto_basic_server/common/autoreg.py
auto_basic_server/common/autosys.py
auto_basic_server/common/autoutil.py
auto_basic_server/common/common_logic.py
auto_basic_server/common/configuration.py
auto_basic_server/common/logger.py
auto_basic_server/common/return_sign.py
auto_basic_server/common/sftputil.py
auto_basic_server/common/timesync.py
auto_basic_server/routes/__init__.py
auto_basic_server/routes/autocfg_blueprint.py
auto_basic_server/routes/autofile_blueprint.py
auto_basic_server/routes/autogui_blueprint.py
auto_basic_server/routes/autoinput_blueprint.py
auto_basic_server/routes/autoproc_blueprint.py
auto_basic_server/routes/autoreg_blueprint.py
auto_basic_server/routes/autosys_blueprint.py
auto_basic_server/routes/configuration_blueprint.py
auto_basic_server/routes/sftputil_blueprint.py
auto_basic_server/routes/timesync_blueprint.py