Metadata-Version: 1.1
Name: auto-basic-server
Version: 0.0.2
Summary: basic server functions
Home-page: UNKNOWN
Author: Liang Yanpeng
Author-email: liangyanpeng@qianxin.com
License: MIT
Platform: UNKNOWN
Classifier: Programming Language :: Python :: 3
